kweb/__init__.py
kweb/browser.py
kweb/config.py
kweb/custom.css
kweb/default.py
kweb/layout_server.py
kweb/py.typed
kweb/server_jupyter.py
kweb/viewer.py
kweb/api/browser.py
kweb/api/viewer.py
kweb/static/client.css
kweb/static/custom.css
kweb/static/viewer.js
kweb/static/bootstrap/bootstrap.bundle.min.js
kweb/static/bootstrap/bootstrap.bundle.min.js.map
kweb/static/bootstrap/bootstrap.min.css
kweb/static/bootstrap/bootstrap.min.css.map
kweb/static/bootstrap/bootstrap.min.js
kweb/static/bootstrap/bootstrap.min.js.map
kweb/static/img/kweb.png
kweb/templates/browser.html
kweb/templates/nav.html
kweb/templates/viewer.html
kweb-2.0.4.dist-info/LICENSE
kweb-2.0.4.dist-info/METADATA
kweb-2.0.4.dist-info/WHEEL
kweb-2.0.4.dist-info/top_level.txt
kweb-2.0.4.dist-info/RECORD
